spellops/__init__.py
spellops/_modidx.py
spellops-0.0.1.dist-info/LICENSE
spellops-0.0.1.dist-info/METADATA
spellops-0.0.1.dist-info/WHEEL
spellops-0.0.1.dist-info/entry_points.txt
spellops-0.0.1.dist-info/top_level.txt
spellops-0.0.1.dist-info/RECORD
