Metadata-Version: 2.1
Name: spellops
Version: 0.0.1
Summary: Harness the power of speLL with spellops to write clean and readable pipelines.
Home-page: https://github.com/artste/spellops
Author: Stefano Giomo
Author-email: artste@users.noreply.github.com
License: Apache Software License 2.0
Keywords: nbdev jupyter notebook python
Classifier: Development Status :: 4 - Beta
Classifier: Intended Audience :: Developers
Classifier: Natural Language :: English
Classifier: Programming Language :: Python :: 3.7
Classifier: Programming Language :: Python :: 3.8
Classifier: Programming Language :: Python :: 3.9
Classifier: Programming Language :: Python :: 3.10
Classifier: Programming Language :: Python :: 3.11
Classifier: Programming Language :: Python :: 3.12
Classifier: License :: OSI Approved :: Apache Software License
Requires-Python: >=3.7
License-File: LICENSE
Requires-Dist: fastcore
Provides-Extra: dev
Requires-Dist: matplotlib; extra == "dev"
Requires-Dist: testcell; extra == "dev"
